patientpop_python_utils/__init__.py
patientpop_python_utils/lambda_utils.py
patientpop_python_utils-0.1.1.dist-info/METADATA
patientpop_python_utils-0.1.1.dist-info/RECORD
patientpop_python_utils-0.1.1.dist-info/WHEEL
patientpop_python_utils-0.1.1.dist-info/top_level.txt
